zennewpy/__init__.py
zennewpy/zennewpy_core.py
zennewpy-0.2.0.dist-info/LICENSE
zennewpy-0.2.0.dist-info/METADATA
zennewpy-0.2.0.dist-info/WHEEL
zennewpy-0.2.0.dist-info/top_level.txt
zennewpy-0.2.0.dist-info/RECORD
