Metadata-Version: 2.1
Name: zennewpy
Version: 0.2.0
Summary: Client to work with Zenodo API
Home-page: https://github.com/yourusername/zennewpy
Author: Marco Mancini
Author-email: marco.mancini@obspm.fr
License: UNKNOWN
Platform: UNKNOWN
Classifier: Programming Language :: Python :: 3
Classifier: License :: OSI Approved :: MIT License
Classifier: Operating System :: OS Independent
License-File: LICENSE
Requires-Dist: requests
Requires-Dist: tabulate
